fronts_toolbox/__init__.py
fronts_toolbox/_fields.py
fronts_toolbox/canny.py
fronts_toolbox/cayula_cornillon.py
fronts_toolbox/heterogeneity_index.py
fronts_toolbox/py.typed
fronts_toolbox/util.py
fronts_toolbox/filters/__init__.py
fronts_toolbox/filters/boa.py
fronts_toolbox/filters/contextual_median.py
fronts_toolbox/filters/median.py
fronts_toolbox/post/__init__.py
fronts_toolbox/post/cc_contour.py
fronts_toolbox-0.1.3.dist-info/licenses/LICENSE
fronts_toolbox-0.1.3.dist-info/METADATA
fronts_toolbox-0.1.3.dist-info/WHEEL
fronts_toolbox-0.1.3.dist-info/top_level.txt
fronts_toolbox-0.1.3.dist-info/RECORD
