Metadata-Version: 2.4
Name: fronts-toolbox
Version: 0.1.3
Summary: Tools to detect fronts
Author-email: Clément Haëck <clement.haeck@locean.ipsl.fr>
Project-URL: Homepage, https://github.com/Descanonge/fronts-toolbox
Classifier: Programming Language :: Python :: 3
Classifier: License :: OSI Approved :: MIT License
Classifier: Operating System :: OS Independent
Classifier: Intended Audience :: Developers
Classifier: Intended Audience :: Science/Research
Classifier: Topic :: Utilities
Requires-Python: >=3.11
License-File: LICENSE
Requires-Dist: numpy>=1.24
Requires-Dist: numba>=0.57
Provides-Extra: docs
Requires-Dist: sphinx==8.2.*; extra == "docs"
Requires-Dist: pydata-sphinx-theme==0.15.*; extra == "docs"
Requires-Dist: sphinx-design; extra == "docs"
Requires-Dist: sphinx-copybutton; extra == "docs"
Requires-Dist: nbsphinx; extra == "docs"
Requires-Dist: jupyterlab; extra == "docs"
Requires-Dist: ipykernel; extra == "docs"
Requires-Dist: matplotlib; extra == "docs"
Provides-Extra: tests
Requires-Dist: pytest>=7.4; extra == "tests"
Requires-Dist: xarray; extra == "tests"
Requires-Dist: dask; extra == "tests"
Requires-Dist: pooch; extra == "tests"
Requires-Dist: netcdf4; extra == "tests"
Requires-Dist: matplotlib; extra == "tests"
Requires-Dist: scipy; extra == "tests"
Requires-Dist: xarray-histogram; extra == "tests"
Requires-Dist: scikit-image; extra == "tests"
Dynamic: license-file
